<?xml version="1.0" encoding="UTF-8"?>

<!DOCTYPE suite SYSTEM "http://testng.org/testng-1.0.dtd">

<suite name="Regression">

<!--  	<listeners>

		<listener class-name="org.uncommons.reportng.HTMLReporter" />

		<listener class-name="org.uncommons.reportng.JUnitXMLReporter" />

		<listener class-name="utilities.Listeners" />

	</listeners>-->

	<test name="NativeApp Test">

		<classes>

		      <class name="Mobile.TC_001App" />

			  <class name="Mobile.TC_002Login" />			

		</classes>

	</test> <!-- Test -->

    </suite> <!-- Suite -->